{"elements": {"0": {"bounding_box": [256, 2512, 329, 2586], "label": 1, "value": "CheckBox"}, "1": {"bounding_box": [257, 2378, 328, 2449], "label": 1, "value": "CheckBox"}, "2": {"bounding_box": [986, 1672, 1199, 1783], "label": 0, "value": "Box"}, "3": {"bounding_box": [1221, 1673, 1363, 1780], "label": 0, "value": "Box"}, "4": {"bounding_box": [1404, 1674, 1708, 1783], "label": 0, "value": "Box"}, "5": {"bounding_box": [256, 2255, 328, 2326], "label": 1, "value": "CheckBox"}, "6": {"bounding_box": [256, 2138, 328, 2209], "label": 1, "value": "CheckBox"}, "7": {"bounding_box": [1692, 1451, 2114, 1573], "label": 0, "value": "Box"}, "8": {"bounding_box": [3100, 1448, 3426, 1575], "label": 0, "value": "Box"}, "9": {"bounding_box": [1741, 1674, 3204, 1780], "label": 0, "value": "Box"}, "10": {"bounding_box": [1258, 3078, 2526, 3105], "label": 2, "value": "Line"}, "11": {"bounding_box": [863, 3785, 2891, 3951], "label": 0, "value": "Box"}, "12": {"bounding_box": [1626, 2877, 2543, 2905], "label": 2, "value": "Line"}, "13": {"bounding_box": [3408, 1451, 4004, 1574], "label": 0, "value": "Box"}, "14": {"bounding_box": [2266, 2562, 2810, 2592], "label": 2, "value": "Line"}, "15": {"bounding_box": [1263, 3438, 3027, 3464], "label": 2, "value": "Line"}, "16": {"bounding_box": [2403, 2418, 3321, 2447], "label": 2, "value": "Line"}, "17": {"bounding_box": [3148, 4919, 3439, 5045], "label": 0, "value": "Box"}, "18": {"bounding_box": [3181, 4525, 4017, 4639], "label": 0, "value": "Box"}, "19": {"bounding_box": [2108, 1446, 3123, 1576], "label": 0, "value": "Box"}, "20": {"bounding_box": [1115, 3574, 3026, 3605], "label": 2, "value": "Line"}, "21": {"bounding_box": [1108, 4447, 3188, 4646], "label": 0, "value": "Box"}, "22": {"bounding_box": [3379, 3775, 4006, 3947], "label": 0, "value": "Box"}, "23": {"bounding_box": [268, 1448, 1704, 1571], "label": 0, "value": "Box"}, "24": {"bounding_box": [3434, 4914, 3996, 5039], "label": 0, "value": "Box"}, "25": {"bounding_box": [2822, 1245, 4005, 1355], "label": 0, "value": "Box"}, "26": {"bounding_box": [318, 4722, 4210, 4844], "label": 0, "value": "Box"}, "27": {"bounding_box": [2361, 4870, 3145, 5041], "label": 0, "value": "Box"}, "28": {"bounding_box": [301, 1243, 2842, 1353], "label": 0, "value": "Box"}, "29": {"bounding_box": [263, 4916, 2162, 5043], "label": 0, "value": "Box"}, "30": {"bounding_box": [1383, 171, 2887, 292], "label": 3, "value": "Employment\n Eligibility\n Verification\n"}, "31": {"bounding_box": [3583, 171, 3832, 257], "label": 3, "value": "USCIS\n"}, "32": {"bounding_box": [3549, 266, 3867, 343], "label": 3, "value": "Form\n "}, "33": {"bounding_box": [1546, 316, 2697, 414], "label": 3, "value": "Department\n  Homeland\n Security\n"}, "34": {"bounding_box": [3437, 352, 3987, 429], "label": 3, "value": "OMB\n No.\n 1615-0047\n"}, "35": {"bounding_box": [1460, 412, 2792, 501], "label": 3, "value": " Citizenship\n and\n Immigration\n Services\n"}, "36": {"bounding_box": [3454, 429, 3961, 498], "label": 3, "value": "Expires\n 03/31/2016\n"}, "37": {"bounding_box": [249, 601, 4004, 689], "label": 3, "value": "> START\n  \n\nHERE.\n Read\n instructions\n carefully\n before\n completing\n this\n form.\n The\n instructions\n must\n  available\n during\n completion\n of this\n form.\n"}, "38": {"bounding_box": [240, 687, 3832, 773], "label": 3, "value": "ANTI-DISCRIMINATION\n NOTICE:\n   illegal\n  discriminate\n against\n work-authorized\n individuals.\n Employers\n CANNOT\n specify\n which\n"}, "39": {"bounding_box": [249, 764, 3789, 855], "label": 3, "value": "document(s)\n they |\n will\n accept |\n from\n  employee.\n The\n refusal\n  hire\n  individual\n because\n the\n documentation\n presented\n has\n future\n"}, "40": {"bounding_box": [249, 842, 1770, 928], "label": 3, "value": "expiration\n date\n may\n also\n constitute\n illegal\n discrimination.\n"}, "41": {"bounding_box": [257, 962, 3892, 1057], "label": 3, "value": "Section\n  Employee\n Information\n and\n Attestation\n (Employees\n must\n \u2018complete\n and\n sign\n Section\n   \u2018Form\n 1-9\n no\n later\n"}, "42": {"bounding_box": [266, 1057, 2259, 1138], "label": 3, "value": "than\n the\n  day\n of\n employment,\n but\n not\n before\n acce,\n \u00bbpting\n Job\n offer.)\n"}, "43": {"bounding_box": [275, 1174, 935, 1248], "label": 3, "value": "Last\n Name\n (Family\n Name)\n"}, "44": {"bounding_box": [1479, 1172, 2122, 1251], "label": 3, "value": "First |\n Name\n (Given |\n Name)\n"}, "45": {"bounding_box": [2483, 1168, 3506, 1246], "label": 3, "value": "Middle\n Initial\n Other\n Names\n Used\n (if.\n any)\n"}, "46": {"bounding_box": [275, 1383, 1177, 1452], "label": 3, "value": "Address\n (Street\n Number .\n and\n Name)\n"}, "47": {"bounding_box": [1710, 1383, 2028, 1452], "label": 3, "value": "Apt.\n Number\n"}, "48": {"bounding_box": [2122, 1375, 2457, 1452], "label": 3, "value": "City\n  Town\n"}, "49": {"bounding_box": [3110, 1383, 3248, 1443], "label": 3, "value": "State\n"}, "50": {"bounding_box": [3428, 1383, 3669, 1452], "label": 3, "value": "Zip\n Code\n"}, "51": {"bounding_box": [275, 1581, 2131, 1660], "label": 3, "value": "Date\n of\n Birth\n (mm/dd/yyyy)\n  Social\n Security\n Number\n E-mail\n Address\n"}, "52": {"bounding_box": [3222, 1598, 3695, 1658], "label": 3, "value": "Telephone\n Number\n"}, "53": {"bounding_box": [240, 1847, 3703, 1925], "label": 3, "value": "  aware\n that\n federal\n law\n provides\n for\n imprisonment\n and/or\n fines\n for\n false\n statements\n  use\n  \u2018false\n documents\n "}, "54": {"bounding_box": [249, 1925, 1555, 2003], "label": 3, "value": "connection\n with\n the\n completion\n  this\n form.\n"}, "55": {"bounding_box": [275, 2036, 2363, 2122], "label": 3, "value": "attest,\n under\n penalty\n of\n perjury,\n that\n  (check\n one\n  the\n following):\n"}, "56": {"bounding_box": [360, 2139, 1168, 2217], "label": 3, "value": " citizen\n of\n the\n United\n States\n"}, "57": {"bounding_box": [360, 2242, 2019, 2330], "label": 3, "value": " noncitizen\n national\n  the\n United\n States\n (See\n instructions)\n"}, "58": {"bounding_box": [369, 2364, 2405, 2460], "label": 3, "value": " lawful\n permanent\n resident\n \u2018(Alien\n Registration\n Number/USCIS\n Number): |\n"}, "59": {"bounding_box": [360, 2509, 2251, 2595], "label": 3, "value": "An alien\n authorized\n  work\n until\n (expiration\n date,\n  applica\n ible.\n mm/dd/yyyy)\n"}, "60": {"bounding_box": [2853, 2509, 3867, 2586], "label": 3, "value": "Some\n aliens\n may\n write\n \"N/A\"\n  this\n field.\n"}, "61": {"bounding_box": [370, 2598, 859, 2676], "label": 3, "value": "(See\n instructions)\n"}, "62": {"bounding_box": [369, 2698, 3712, 2784], "label": 3, "value": "For\n aliens\n authorized\n  work,\n provide\n your\n  Registration\n Number/USCIS\n Number\n  Form\n I-94\n Admission\n Number:\n"}, "63": {"bounding_box": [360, 2818, 1632, 2904], "label": 3, "value": " Alien\n Registration\n Number/USCIS\n Number:\n"}, "64": {"bounding_box": [971, 2921, 1108, 3007], "label": 3, "value": ""}, "65": {"bounding_box": [3231, 2956, 3944, 3033], "label": 3, "value": "Do\n Not.\n Write\n  This\n Space\n"}, "66": {"bounding_box": [3420, 2896, 3755, 2956], "label": 3, "value": "3-D\n Barcode\n"}, "67": {"bounding_box": [360, 3033, 1271, 3110], "label": 3, "value": " Form\n |-94\n Admission\n Number:\n"}, "68": {"bounding_box": [429, 3179, 3016, 3265], "label": 3, "value": " you\n obtained\n your\n admission\n number\n from\n CBP\n  connection\n with\n your\n arrival\n in\n the\n United\n"}, "69": {"bounding_box": [421, 3257, 1236, 3345], "label": 3, "value": "States.\n include\n the\n following:\n"}, "70": {"bounding_box": [498, 3385, 1246, 3471], "label": 3, "value": "Foreign\n Passport\n Number:\n"}, "71": {"bounding_box": [498, 3532, 1082, 3616], "label": 3, "value": "Country\n of\n Issuance:\n"}, "72": {"bounding_box": [429, 3652, 3540, 3729], "label": 3, "value": "Some\n aliens\n may\n write\n  on\n the\n Foreign\n Passport\n Number\n and\n Country\n of\n Issuance\n fields.\n (See\n instructions)\n"}, "73": {"bounding_box": [275, 3832, 859, 3901], "label": 3, "value": "Signature\n of\n Employee:\n"}, "74": {"bounding_box": [2887, 3832, 3377, 3901], "label": 3, "value": "Date\n (mm/dd/yyyy):\n"}, "75": {"bounding_box": [258, 4028, 3807, 4124], "label": 3, "value": "Preparer\n and/or\n Transl\n slator\n Certification\n (To\n  completed\n and |\n signed\n  Section\n  prepared\n   person\n other\n \u2018than\n the\n"}, "76": {"bounding_box": [266, 4125, 584, 4185], "label": 3, "value": "employee.)\n"}, "77": {"bounding_box": [275, 4228, 3944, 4314], "label": 3, "value": "attest,\n under\n penalty\n of\n perjury,\n that\n have\n assisted\n  the\n completion\n  \u2018this\n form\n and\n that\n  the\n best\n   knowledge\n the\n"}, "78": {"bounding_box": [249, 4314, 1177, 4382], "label": 3, "value": "information\n  true\n and\n correct.\n"}, "79": {"bounding_box": [266, 4457, 1151, 4528], "label": 3, "value": "Signature\n of\n Preparer |\n  Translator:\n"}, "80": {"bounding_box": [3214, 4460, 3703, 4528], "label": 3, "value": "Date\n (mm/dd/yyyy):\n"}, "81": {"bounding_box": [257, 4657, 902, 4726], "label": 3, "value": "\u2018Last\n Name\n (Family\n Name)\n"}, "82": {"bounding_box": [2423, 4655, 3066, 4729], "label": 3, "value": "First\n Name\n (Given\n Name)\n"}, "83": {"bounding_box": [266, 4855, 1160, 4915], "label": 3, "value": "Address\n (Street\n Number\n and\n Name)\n"}, "84": {"bounding_box": [2148, 4855, 2466, 4915], "label": 3, "value": "City\n  Town\n"}, "85": {"bounding_box": [3162, 4855, 3300, 4915], "label": 3, "value": "State\n"}, "86": {"bounding_box": [3446, 4855, 3678, 4915], "label": 3, "value": "Zip\n Code\n"}, "87": {"bounding_box": [1387, 5136, 1508, 5181], "label": 3, "value": "[STOP]\n"}, "88": {"bounding_box": [1658, 5113, 2672, 5207], "label": 3, "value": "Employer\n Completes\n Next\n Page\n"}, "89": {"bounding_box": [2827, 5130, 2939, 5182], "label": 3, "value": "Ald\n"}}, "form_id": [0, 1, 2, 3, 4, 5, 6, 7, 8, 9, 10, 11, 12, 13, 14, 15, 16, 17, 18, 19, 20, 21, 22, 23, 24, 25, 26, 27, 28, 29], "text_id": [30, 31, 32, 33, 34, 35, 36, 37, 38, 39, 40, 41, 42, 43, 44, 45, 46, 47, 48, 49, 50, 51, 52, 53, 54, 55, 56, 57, 58, 59, 60, 61, 62, 63, 64, 65, 66, 67, 68, 69, 70, 71, 72, 73, 74, 75, 76, 77, 78, 79, 80, 81, 82, 83, 84, 85, 86, 87, 88, 89], "text_count": 60, "box_count": 20, "checkbox_count": 4, "line_count": 6}